fewsxml/__init__.py
fewsxml/api_fx_read.py
fewsxml/api_fx_write.py
fewsxml/api_model_construction.py
fewsxml/models.py
fewsxml-0.2.0.dist-info/licenses/LICENSE
fewsxml-0.2.0.dist-info/METADATA
fewsxml-0.2.0.dist-info/WHEEL
fewsxml-0.2.0.dist-info/top_level.txt
fewsxml-0.2.0.dist-info/RECORD
