Metadata-Version: 2.4
Name: fewsxml
Version: 0.2.0
Summary: A library for reading and writing XML files to interact with Delft-FEWS.
Home-page: https://gitlab.com/FaridAlavi/fewsxml
Author: Farid Alavi
Author-email: farid.alavi@deltares.nl
Classifier: Programming Language :: Python :: 3
Classifier: License :: OSI Approved :: Apache Software License
Classifier: Operating System :: OS Independent
Requires-Python: >=3.11
License-File: LICENSE
Requires-Dist: pydantic
Dynamic: author
Dynamic: author-email
Dynamic: classifier
Dynamic: description
Dynamic: description-content-type
Dynamic: home-page
Dynamic: license-file
Dynamic: requires-dist
Dynamic: requires-python
Dynamic: summary
